{
	"name": "spr_player",
	"plugin-id": "Sprite",
	"sid": 759583840248850,
	"isGlobal": false,
	"instanceVariables": [
		{
			"name": "follow_distance",
			"type": "number",
			"desc": "Distance between the player and the camera.",
			"sid": 294494463809146
		},
		{
			"name": "speed_x",
			"type": "number",
			"desc": "Current speed at which the player is sliding horizontally.",
			"sid": 669542307511205
		},
		{
			"name": "acceleration_x",
			"type": "number",
			"desc": "Horizontal acceleration.",
			"sid": 140777818536785
		},
		{
			"name": "deacceleration_x",
			"type": "number",
			"desc": "Horizontal deacceleration.",
			"sid": 776551426811193
		},
		{
			"name": "max_speed_x",
			"type": "number",
			"desc": "Maximum horizontal speed.",
			"sid": 999810604337480
		},
		{
			"name": "speed_z",
			"type": "number",
			"desc": "Current speed at which the player is sliding forward.",
			"sid": 736264282461000
		},
		{
			"name": "max_speed_z",
			"type": "number",
			"desc": "Maximum forward speed.",
			"sid": 947216566297391
		},
		{
			"name": "min_speed_z",
			"type": "number",
			"desc": "Minimum forward speed.",
			"sid": 460730248650549
		},
		{
			"name": "acceleration_z",
			"type": "number",
			"desc": "Acceleration when the player isn't boosting or getting hit.",
			"sid": 788460529716688
		},
		{
			"name": "speed_z_step",
			"type": "number",
			"desc": "How much the Z speed increases/decreases when the player boosts/gets hit.",
			"sid": 123834011093988
		}
	],
	"behaviorTypes": [
		{
			"behaviorId": "Tween",
			"name": "Tween",
			"sid": 979238549909622
		}
	],
	"effectTypes": [],
	"animations": {
		"items": [
			{
				"frames": [
					{
						"width": 128,
						"height": 123,
						"originX": 0.4762868881225586,
						"originY": -0.04402249059175105,
						"originalSource": "C:\\Users\\gamedev\\Desktop\\penguin.png",
						"exportFormat": "png",
						"exportQuality": 0.8,
						"imageSpriteId": 4,
						"collisionPoly": {
							"points": [
								0.3215534687042235,
								0.41821366062163495,
								0.6587929725646973,
								0.3962024153257594,
								0.7341759204864502,
								0.5634878795744135,
								0.6049633026123047,
								0.8018837455874063,
								0.4841606616973877,
								0.9139446827742121,
								0.33235311508178716,
								0.8208415754591811,
								0.2303004264831543,
								0.5634878795744135
							]
						},
						"duration": 1
					},
					{
						"width": 125,
						"height": 123,
						"originX": 0.464,
						"originY": -0.043983739837398374,
						"originalSource": "C:\\Users\\gamedev\\Desktop\\penguin02.png",
						"exportFormat": "png",
						"exportQuality": 0.8,
						"imageSpriteId": 9,
						"collisionPoly": {
							"points": [
								0.3215534687042235,
								0.41821366062163495,
								0.6587929725646973,
								0.3962024153257594,
								0.7341759204864502,
								0.5634878795744135,
								0.7143383026123047,
								0.8100138268882193,
								0.4802544116973877,
								0.9993105364327487,
								0.26204061508178716,
								0.8452318193616202,
								0.2303004264831543,
								0.5634878795744135
							]
						},
						"duration": 1
					},
					{
						"width": 119,
						"height": 123,
						"originX": 0.46218487394957986,
						"originY": -0.043983739837398374,
						"originalSource": "C:\\Users\\gamedev\\Desktop\\penguin03.png",
						"exportFormat": "png",
						"exportQuality": 0.8,
						"imageSpriteId": 11,
						"collisionPoly": {
							"points": [
								0.3215534687042235,
								0.41821366062163495,
								0.6587929725646973,
								0.3962024153257594,
								0.7341759204864502,
								0.5634878795744135,
								0.7143383026123047,
								0.8100138268882193,
								0.4802544116973877,
								0.9993105364327487,
								0.26204061508178716,
								0.8452318193616202,
								0.2303004264831543,
								0.5634878795744135
							]
						},
						"duration": 1
					}
				],
				"sid": 992429274012689,
				"name": "center",
				"isLooping": true,
				"isPingPong": false,
				"repeatCount": 1,
				"repeatTo": 0,
				"speed": 12
			}
		],
		"subfolders": []
	}
}