{
	"name": "spr_snow_clump",
	"plugin-id": "Sprite",
	"sid": 974501636719535,
	"isGlobal": false,
	"instanceVariables": [],
	"behaviorTypes": [],
	"effectTypes": [],
	"animations": {
		"items": [
			{
				"frames": [
					{
						"width": 111,
						"height": 114,
						"originX": 0.4774774774774775,
						"originY": 0.008771929824561403,
						"originalSource": "C:\\Users\\gamedev\\Desktop\\clump.png",
						"exportFormat": "png",
						"exportQuality": 0.8,
						"imageSpriteId": 0,
						"collisionPoly": {
							"points": [
								0,
								0.029448621553884717,
								0.5225225225225225,
								0,
								1,
								0.09602130325814541,
								1,
								0.5087719298245614,
								1,
								1,
								0,
								1,
								0,
								0.5087719298245614
							]
						},
						"duration": 1
					}
				],
				"sid": 909630410028634,
				"name": "Animation 1",
				"isLooping": false,
				"isPingPong": false,
				"repeatCount": 1,
				"repeatTo": 0,
				"speed": 5
			}
		],
		"subfolders": []
	}
}